Workbook

Sheet Creators
A1: SponsorSync - Creator Roster (mock data for prototype)
A2: 18 fictional creators. Fill or edit the yellow columns; the shaded columns are formulas and recalculate on their own. No real person appears in this file.
A4: creator_id | B4: name | C4: handle | D4: category | E4: tier | F4: subscribers | G4: avg_views | H4: engagement_rate | I4: view_to_sub_ratio | J4: channel_verified | K4: safety_score | L4: audience_age | M4: audience_gender | N4: top_country | O4: upload_cadence | P4: avg_length_min | Q4: rate_integrated | R4: rate_dedicated | S4: rate_short | T4: cost_per_1k_views | U4: demo_note | V4: avatar_initials | W4: avatar_color | X4: bio | Y4: languages | Z4: formats_offered | AA4: turnaround_days | AB4: worked_with_categories
A5: maya-chen | B5: Maya Chen | C5: @mayaeats | D5: Food & Beverage | E5: Micro | F5: 84000 | G5: 41000 | H5: 0.072 | I5: =G5/F5 | J5: TRUE | K5: 96 | L5: 25-34 | M5: 61% F | N5: US | O5: 2 / week | P5: 12 | Q5: 1200 | R5: 2500 | S5: 600 | T5: =ROUND(R5/G5*1000,1) | U5: Replaces the Lady Gaga placeholder. Keep the same rates so nothing else breaks. | V5: MC | W5: #C0392B | X5: Grocery-aisle taste tests and honest pantry cooking for people who cook on weeknights. | Y5: English | Z5: Integrated; Dedicated; Short | AA5: 10 | AB5: Food & Beverage; Kitchenware
A6: diego-alvarez | B6: Diego Alvarez | C6: @diegocooks | D6: Cooking | E6: Mid-tier | F6: 156000 | G6: 62000 | H6: 0.051 | I6: =G6/F6 | J6: TRUE | K6: 90 | L6: 25-44 | M6: 54% M | N6: US | O6: 1 / week | P6: 18 | Q6: 1800 | R6: 4200 | S6: 900 | T6: =ROUND(R6/G6*1000,1) | U6: Existing profile — unchanged. | V6: DA | W6: #27AE60 | X6: Restaurant technique translated for a home kitchen, filmed slowly and explained properly. | Y6: English; Spanish | Z6: Integrated; Dedicated | AA6: 14 | AB6: Kitchenware; Grocery; Appliances
A7: priya-nair | B7: Priya Nair | C7: @priyawellness | D7: Health & Lifestyle | E7: Micro | F7: 22000 | G7: 12000 | H7: 0.094 | I7: =G7/F7 | J7: FALSE | K7: 98 | L7: 25-34 | M7: 78% F | N7: US | O7: 2 / week | P7: 10 | Q7: 450 | R7: 900 | S7: 250 | T7: =ROUND(R7/G7*1000,1) | U7: Existing profile — unchanged. Unverified channel, useful contrast. | V7: PN | W7: #6C3FC5 | X7: Unglamorous wellness routines that a working person can actually keep up. | Y7: English; Hindi | Z7: Integrated; Short | AA7: 7 | AB7: Wellness; Activewear
A8: jordan-blake | B8: Jordan Blake | C8: @jordanreviews | D8: Tech Reviews | E8: Mid-tier | F8: 310000 | G8: 140000 | H8: 0.043 | I8: =G8/F8 | J8: TRUE | K8: 85 | L8: 18-34 | M8: 71% M | N8: US | O8: 2 / week | P8: 15 | Q8: 3500 | R8: 8000 | S8: 1500 | T8: =ROUND(R8/G8*1000,1) | U8: Existing profile — unchanged. | V8: JB | W8: #2C3E50 | X8: Consumer tech tested on a budget, with the spec-sheet marketing stripped out. | Y8: English | Z8: Integrated; Dedicated; Short | AA8: 14 | AB8: Consumer Electronics; Accessories
A9: sofia-reyes | B9: Sofia Reyes | C9: @sofiabakes | D9: Food & Beverage | E9: Nano | F9: 4200 | G9: 3100 | H9: 0.118 | I9: =G9/F9 | J9: FALSE | K9: 97 | L9: 18-34 | M9: 82% F | N9: US | O9: 1 / week | P9: 9 | Q9: 180 | R9: 340 | S9: 110 | T9: =ROUND(R9/G9*1000,1) | U9: Cheapest entry point. Shows an SMB can start a sponsorship for under $400. | V9: SR | W9: #E67E22 | X9: Small-kitchen baking. Nothing here needs equipment you do not already own. | Y9: English; Spanish | Z9: Integrated; Short | AA9: 7 | AB9: Baking; Grocery
A10: tom-okafor | B10: Tom Okafor | C10: @tomsdesksetup | D10: Tech Reviews | E10: Nano | F10: 7800 | G10: 5400 | H10: 0.089 | I10: =G10/F10 | J10: TRUE | K10: 92 | L10: 18-34 | M10: 68% M | N10: UK | O10: 1 / week | P10: 11 | Q10: 260 | R10: 520 | S10: 160 | T10: =ROUND(R10/G10*1000,1) | U10: Non-US audience — lets you demo a geography filter. | V10: TO | W10: #34495E | X10: Desk setups under a real budget, with the parts that were not worth it named out loud. | Y10: English | Z10: Integrated; Dedicated | AA10: 10 | AB10: Office Furniture; Accessories
A11: hannah-weiss | B11: Hannah Weiss | C11: @hannahliftsheavy | D11: Fitness | E11: Nano | F11: 9100 | G11: 6800 | H11: 0.102 | I11: =G11/F11 | J11: FALSE | K11: 94 | L11: 25-34 | M11: 58% F | N11: US | O11: 2 / week | P11: 13 | Q11: 300 | R11: 620 | S11: 190 | T11: =ROUND(R11/G11*1000,1) | U11: Sits right under the 10K Nano/Micro boundary — good for testing tier filters. | V11: HW | W11: #16A085 | X11: Strength training explained from first principles, with form checks from viewers. | Y11: English; German | Z11: Integrated; Short | AA11: 7 | AB11: Fitness Equipment; Supplements
A12: luis-moreno | B12: Luis Moreno | C12: @luisplaysindie | D12: Gaming | E12: Nano | F12: 6500 | G12: 12400 | H12: 0.141 | I12: =G12/F12 | J12: TRUE | K12: 88 | L12: 18-24 | M12: 64% M | N12: US | O12: 4 / week | P12: 3 | Q12: 280 | R12: 560 | S12: 200 | T12: =ROUND(R12/G12*1000,1) | U12: KEY DEMO CASE: avg views are 1.9x subscriber count (Shorts-driven). Proves AI Match ranks on fit, not follower count. | V12: LM | W12: #8E44AD | X12: Short-form indie game finds, three or four a week, mostly things nobody is covering. | Y12: English; Spanish | Z12: Short; Integrated | AA12: 5 | AB12: Gaming Peripherals; Game Publishers
A13: nia-thompson | B13: Nia Thompson | C13: @niathreadcount | D13: Fashion & Beauty | E13: Micro | F13: 38000 | G13: 19000 | H13: 0.068 | I13: =G13/F13 | J13: TRUE | K13: 93 | L13: 18-34 | M13: 88% F | N13: US | O13: 2 / week | P13: 12 | Q13: 700 | R13: 1500 | S13: 420 | T13: =ROUND(R13/G13*1000,1) | U13: Strongest gender skew in the roster — useful for audience-targeting demos. | V13: NT | W13: #D35D8B | X13: Thrift flips and capsule wardrobes for people who want fewer, better clothes. | Y13: English | Z13: Integrated; Dedicated; Short | AA13: 10 | AB13: Apparel; Resale Platforms
A14: kenji-watanabe | B14: Kenji Watanabe | C14: @kenjibuildsbikes | D14: Outdoor & Gear | E14: Micro | F14: 51000 | G14: 33000 | H14: 0.081 | I14: =G14/F14 | J14: TRUE | K14: 95 | L14: 25-44 | M14: 73% M | N14: US | O14: 1 / week | P14: 20 | Q14: 950 | R14: 2100 | S14: 520 | T14: =ROUND(R14/G14*1000,1) | U14: 65% view-to-sub ratio — unusually loyal audience. Second-best 'fit beats size' example. | V14: KW | W14: #2980B9 | X14: Bike builds and teardowns with real mileage behind every recommendation. | Y14: English; Japanese | Z14: Dedicated; Integrated | AA14: 21 | AB14: Cycling; Outdoor Gear
A15: amara-osei | B15: Amara Osei | C15: @amaraparents | D15: Parenting & Family | E15: Micro | F15: 29000 | G15: 11000 | H15: 0.054 | I15: =G15/F15 | J15: FALSE | K15: 99 | L15: 30-44 | M15: 76% F | N15: US | O15: 1 / week | P15: 14 | Q15: 560 | R15: 1200 | S15: 340 | T15: =ROUND(R15/G15*1000,1) | U15: Highest safety score. Brand-safe category for risk-averse sponsors. | V15: AO | W15: #F39C12 | X15: Parenting content with real portions, real budgets and no staged mornings. | Y15: English; French | Z15: Integrated | AA15: 14 | AB15: Baby Care; Grocery; Household
A16: ryan-novak | B16: Ryan Novak | C16: @ryannovakfinance | D16: Personal Finance | E16: Micro | F16: 67000 | G16: 24000 | H16: 0.041 | I16: =G16/F16 | J16: TRUE | K16: 82 | L16: 25-34 | M16: 69% M | N16: US | O16: 2 / week | P16: 16 | Q16: 1000 | R16: 2200 | S16: 550 | T16: =ROUND(R16/G16*1000,1) | U16: KEY DEMO CASE: finance category, safety 82. Best subject for the AI content-review screen (unsubstantiated return claims). | V16: RN | W16: #7F8C8D | X16: Personal finance without jargon, aimed at people starting from zero. | Y16: English | Z16: Integrated; Dedicated | AA16: 10 | AB16: Fintech; Banking
... A54: felicity-obi | B54: Felicity Obi | C54: @felicitythrifts | D54: Fashion & Beauty | E54: Nano | F54: 6900 | G54: 4000 | H54: 0.109 | I54: =G54/F54 | J54: FALSE | K54: 94 | L54: 18-34 | M54: 88% F | N54: US | O54: 2 / week | P54: 9 | Q54: 190 | R54: 400 | S54: 100 | T54: =ROUND(R54/G54*1000,1) | U54: Nano fashion, strongest gender skew, cheap entry. | V54: FO | W54: #A93226 | X54: Thrift hauls and refashioning for a tiny budget. | Y54: English | Z54: Integrated; Dedicated; Short | AA54: 8 | AB54: Apparel; Resale Platforms
A56: All values above are invented for demonstration. Rates follow a decreasing cost-per-1,000-views curve as audience size grows, which is how real creator rate cards behave. Tier boundaries: Nano under 10K subscribers, Micro 10K-100K, Mid-tier 100K-500K.
A58: FLAG LEGEND
A59: K column green | B59: Safety 90+ - no manual review needed.
A60: K column amber | B60: Safety 80-89 - review the content before signing.
A61: K column red | B61: Safety under 80 - manual review required. Only Marcus Hale, deliberately.
A62: H column amber | B62: Engagement below the floor for this creator's tier.
A63: T column red | B63: Cost per 1,000 views above the poor-value threshold for this tier.

Sheet RecentVideos
A1: Recent videos - 3 per creator
A2: This is what the AI reads to score campaign fit and to draft a brief written for one specific creator. Without it, a personalized brief has nothing to personalize from.
A4: creator_id | B4: video_title | C4: days_ago | D4: views | E4: likes | F4: comments | G4: video_engagement_rate | H4: had_sponsor | I4: topic_tags
A5: maya-chen | B5: I Tried 6 Grocery-Store Olive Oils - Blind Taste Test | C5: 8 | D5: 52000 | E5: 3900 | F5: 410 | G5: =(E5+F5)/D5 | H5: FALSE | I5: taste-test; pantry; comparison
A6: maya-chen | B6: The $9 Pantry Dinner I Make Every Week | C6: 17 | D6: 38000 | E6: 2800 | F6: 290 | G6: =(E6+F6)/D6 | H6: TRUE | I6: budget; weeknight; recipe
A7: maya-chen | B7: Why Your Cold Brew Tastes Bitter (3 Fixes) | C7: 26 | D7: 44000 | E7: 3300 | F7: 355 | G7: =(E7+F7)/D7 | H7: FALSE | I7: coffee; technique; troubleshooting
A8: diego-alvarez | B8: Restaurant-Style Carnitas in a Home Oven | C8: 5 | D8: 71000 | E8: 3600 | F8: 480 | G8: =(E8+F8)/D8 | H8: FALSE | I8: recipe; technique; mexican
A9: diego-alvarez | B9: I Cooked Every Recipe From One Cookbook for a Week | C9: 14 | D9: 58000 | E9: 2900 | F9: 390 | G9: =(E9+F9)/D9 | H9: FALSE | I9: challenge; cookbook
A10: diego-alvarez | B10: The Only 5 Knives You Actually Need | C10: 23 | D10: 64000 | E10: 3400 | F10: 520 | G10: =(E10+F10)/D10 | H10: TRUE | I10: gear; kitchen-tools; buying-guide
A11: priya-nair | B11: My Actual 6am Routine (No 5am Nonsense) | C11: 6 | D11: 15000 | E11: 1400 | F11: 180 | G11: =(E11+F11)/D11 | H11: FALSE | I11: routine; morning; realistic
A12: priya-nair | B12: What I Eat in a Week on a Student Budget | C12: 12 | D12: 11000 | E12: 1100 | F12: 140 | G12: =(E12+F12)/D12 | H12: FALSE | I12: budget; nutrition; student
A13: priya-nair | B13: 3 Stretches That Fixed My Desk Neck | C13: 21 | D13: 13000 | E13: 1250 | F13: 160 | G13: =(E13+F13)/D13 | H13: TRUE | I13: mobility; desk-health; how-to
A14: jordan-blake | B14: This $200 Laptop Shouldn't Be This Good | C14: 4 | D14: 168000 | E14: 7100 | F14: 1200 | G14: =(E14+F14)/D14 | H14: FALSE | I14: budget-tech; laptop; review
A15: jordan-blake | B15: I Used Only Budget Headphones for 30 Days | C15: 13 | D15: 129000 | E15: 5400 | F15: 890 | G15: =(E15+F15)/D15 | H15: TRUE | I15: audio; long-term-test
A16: jordan-blake | B16: Every USB-C Cable Is Lying to You | C16: 22 | D16: 145000 | E16: 6200 | F16: 1050 | G16: =(E16+F16)/D16 | H16: FALSE | I16: accessories; testing; explainer
... A154: felicity-obi | B154: The Secondhand Finds Worth It | C154: 21 | D154: 4000 | E154: 420 | F154: 45 | G154: =(E154+F154)/D154 | H154: FALSE | I154: thrift; resale; haul
A156: days_ago is counted from the day the prototype is demoed, so recency stays correct without hardcoding dates.

Sheet Field guide
A1: How to use this file
A3: WHO EDITS WHAT
A4: Yellow-tinted columns | B4: Edit freely - these are the values you invent.
A5: Shaded lavender columns | B5: Formulas. Leave alone; they recalculate from the columns beside them.
A6: creator_id | B6: Never change once the developer has loaded the file - RecentVideos joins on it.
A8: FIELD DEFINITIONS
A9: tier | B9: Nano = under 10K subs, Micro = 10K-100K, Mid-tier = 100K-500K. Must match the filter buttons on /creators.
A10: engagement_rate | B10: (likes + comments) / views, stored as a fraction. 0.072 displays as 7.2%.
A11: view_to_sub_ratio | B11: avg_views / subscribers. Above 100% means the creator reaches well beyond subscribers, usually via Shorts.
A12: channel_verified | B12: TRUE = YouTube channel ownership confirmed. Separate from 'Business verified', which applies to sponsors.
A13: safety_score | B13: 0-100 brand-safety rating. Keep real spread: this roster runs 71 to 99. All-high scores make the metric look decorative.
A14: rate_integrated | B14: Price for a mention inside a longer video.
A15: rate_dedicated | B15: Price for a whole video about the product.
A16: rate_short | B16: Price for a YouTube Short.
A17: cost_per_1k_views | B17: rate_dedicated / avg_views x 1000. Should trend DOWN as audience grows - that is how real rate cards work.
A19: FOUR CREATORS WORTH DEMOING
A20: Luis Moreno | B20: 6.5K subs, 12.4K avg views. Reach is 1.9x his subscriber count. The single best proof that AI Match scores fit, not follower count.
A21: Marcus Hale | B21: 92K subs but 3.2% engagement and safety 71. AI Match should rank him low despite the big number.
A22: Ryan Novak | B22: Personal finance, safety 82. Best subject for the content-review screen - return claims are the classic legal risk.
A23: Isabel Cruz | B23: Food & Beverage, 8.4% engagement, mid-tier reach. Should come out #1 for the demo campaign.
A25: KEEP IN MIND
A26: No real people | B26: Every name here is invented. Do not reintroduce a real creator or celebrity - inventing follower counts and prices for a real person carries a name-and-likeness risk, and judges will notice the numbers are fake.
A27: Coverage over volume | B27: The point of 18 profiles is that every filter combination returns results. An empty results page during a live demo is worse than a short list.
A28: Field names | B28: Confirm these against src/lib/mockData.js before the developer imports. If the existing keys differ, rename the headers here rather than changing the code.

Sheet Schema
A1: Metadata schema
A2: One row per field. The API source column is what makes the mock-to-live swap mechanical: every field either maps to a YouTube Data API response path, is derived from fields that do, or is owned by SponsorSync itself.
A4: field | B4: entity | C4: type | D4: format / unit | E4: allowed values or range | F4: required | G4: origin | H4: YouTube Data API source | I4: notes
A5: creator_id | B5: creator | C5: string | D5: kebab-case | E5: unique, no spaces | F5: yes | G5: SponsorSync | H5: derived from channel id | I5: Primary key. RecentVideos joins on it. Never reassign.
A6: name | B6: creator | C6: string | D6: display name | E6: 2-60 chars | F6: yes | G6: YouTube | H6: channels.list > snippet.title | I6: Channel display name, not legal name.
A7: handle | B7: creator | C7: string | D7: @handle | E7: starts with @, unique | F7: yes | G7: YouTube | H7: channels.list > snippet.customUrl | I7: Stable identifier users recognise.
A8: category | B8: creator | C8: enum | D8: text | E8: see Feature benchmarks tab | F8: yes | G8: SponsorSync | H8: inferred from videos.list > snippet.categoryId + titles | I8: YouTube's own category list is too coarse for sponsorship matching, so we classify ourselves.
A9: tier | B9: creator | C9: enum | D9: text | E9: Nano / Micro / Mid-tier | F9: yes | G9: derived | H9: binned from subscriberCount | I9: Boundaries at 10K and 100K. Must match the filter buttons on /creators.
A10: subscribers | B10: creator | C10: integer | D10: #,##0 | E10: 0 - 500,000,000 | F10: yes | G10: YouTube | H10: channels.list > statistics.subscriberCount | I10: Rounded by the API to 3 significant figures, and absent entirely when the channel hides it. See cleaning rule C4.
A11: avg_views | B11: creator | C11: integer | D11: #,##0 | E11: 0 - 100,000,000 | F11: yes | G11: derived | H11: mean of videos.list > statistics.viewCount | I11: Mean of the last N public videos. Excludes Shorts unless flagged - mixing them distorts the mean badly.
A12: engagement_rate | B12: creator | C12: decimal | D12: 0.0% | E12: 0.000 - 0.300 | F12: yes | G12: derived | H12: (likeCount + commentCount) / viewCount | I12: Stored as a fraction. Above 30% almost always means bot activity or a tiny denominator.
A13: view_to_sub_ratio | B13: creator | C13: decimal | D13: 0% | E13: 0.00 - 5.00 | F13: no | G13: derived | H13: avg_views / subscriberCount | I13: Above 1.00 means reach exceeds the subscriber base, typically via Shorts or search.
A14: channel_verified | B14: creator | C14: boolean | D14: TRUE / FALSE | E14: TRUE / FALSE | F14: yes | G14: SponsorSync | H14: OAuth channel-ownership handshake | I14: Distinct from a sponsor's business verification. Do not conflate the two in the UI.
A15: safety_score | B15: creator | C15: integer | D15: 0-100 | E15: 0 - 100 | F15: yes | G15: SponsorSync | H15: model output over titles, tags, comments | I15: Composite brand-safety rating. Needs a documented rubric before launch.
... A31: topic_tags | B31: video | C31: list | D31: semicolon-separated | E31: 1-6 tags | F31: no | G31: derived | H31: snippet.tags + title classification | I31: Semicolon rather than comma so the field survives a CSV round-trip.

Sheet Cleaning rules
A1: Cleaning and validation rules
A2: Rules C1-C6 are the ones real YouTube data will break on. The validation panel below runs live against the Creators and RecentVideos tabs, so a bad edit shows up before the developer imports it.
A4: rule | B4: applies to | C4: the rule | D4: why it matters | E4: action on failure
A5: C1 | B5: creator_id | C5: Unique, lowercase, kebab-case, no whitespace. | D5: It is the join key to RecentVideos. A duplicate silently merges two creators' video histories. | E5: Reject the row, do not import.
A6: C2 | B6: engagement_rate | C6: Recompute from the video rows rather than trusting a stored value; flag anything above 30%. | D6: A stored rate can drift from its inputs after an edit. Extreme values usually mean bot engagement or a near-zero denominator. | E6: Recompute; flag outliers for review.
A7: C3 | B7: avg_views | C7: Exclude Shorts from the mean unless the channel is Shorts-led, and say which basis was used. | D7: A single viral Short can triple the mean and make the rate card look like a bargain that does not exist. | E7: Store both figures; label which one the UI shows.
A8: C4 | B8: subscribers | C8: Treat as approximate. Handle the hidden-count case explicitly. | D8: The API rounds subscriber counts to three significant figures, and returns nothing at all when a channel hides the number. Zero and unknown are not the same thing. | E8: Null, not 0. Assign tier from avg_views instead.
A9: C5 | B9: likes / comments | C9: Null when hidden or disabled; never coerce to zero. | D9: Coercing to zero drags engagement_rate down and makes a healthy creator look dead. | E9: Null, and exclude that video from the mean.
A10: C6 | B10: audience_age / gender / country | C10: Only present with the creator's analytics consent. | D10: These come from YouTube Analytics, which the channel owner must authorise. Most creators in a cold directory will have none of it. | E10: Fall back to a neutral audience score; never guess.
A11: C7 | B11: rate_* fields | C11: Positive, and rate_short < rate_integrated < rate_dedicated. | D11: An inverted ladder is the commonest data-entry slip and makes the whole rate card untrustworthy. | E11: Flag the row; ask the creator to confirm.
A12: C8 | B12: safety_score | C12: Integer 0-100, with real spread across the roster. | D12: If every creator scores above 90 the metric carries no information and reviewers stop reading it. | E12: Flag if the roster standard deviation is too low.
A13: C9 | B13: category | C13: Must be one of the values on the Feature benchmarks tab. | D13: A free-text category cannot be matched, filtered or benchmarked against a tier norm. | E13: Map to the nearest listed value or reject.
A14: C10 | B14: video rows | C14: At least 3 recent videos per creator, most recent within 30 days. | D14: A personalized brief and a fit score both need recent content. Below 3 videos the signal is noise. | E14: Exclude the creator from AI Match.
A17: LIVE VALIDATION
A18: check | B18: expected | C18: actual | D18: status
A19: Creator rows | B19: 18 | C19: =COUNTA(Creators!$A$5:$A$22) | D19: =IF(C19=18,"PASS","CHECK")
A20: Duplicate creator_id | B20: 0 | C20: =COUNTA(Creators!$A$5:$A$22)-SUMPRODUCT(1/COUNTIF(Creators!$A$5:$A$22,Creators!$A$5:$A$22)) | D20: =IF(C20=0,"PASS","CHECK")
A21: Engagement rate above 30% | B21: 0 | C21: =COUNTIF(Creators!$H$5:$H$22,">0.3") | D21: =IF(C21=0,"PASS","CHECK")
A22: Inverted rate ladder | B22: 0 | C22: =SUMPRODUCT(--(Creators!$S$5:$S$22>=Creators!$Q$5:$Q$22))+SUMPRODUCT(--(Creators!$Q$5:$Q$22>=Creators!$R$5:$R$22)) | D22: =IF(C22=0,"PASS","CHECK")
A23: Safety score out of range | B23: 0 | C23: =COUNTIF(Creators!$K$5:$K$22,"<0")+COUNTIF(Creators!$K$5:$K$22,">100") | D23: =IF(C23=0,"PASS","CHECK")
A24: Safety score spread (max-min) | B24: at least 20 | C24: =MAX(Creators!$K$5:$K$22)-MIN(Creators!$K$5:$K$22) | D24: ="review"
A25: Creators with fewer than 3 videos | B25: 0 | C25: =SUMPRODUCT(--(COUNTIF(RecentVideos!$A$5:$A$58,Creators!$A$5:$A$22)<3)) | D25: =IF(C25=0,"PASS","CHECK")
A26: Most recent video older than 30 days | B26: 0 | C26: =COUNTIF(RecentVideos!$C$5:$C$58,">30") | D26: =IF(C26=0,"PASS","CHECK")
A27: Nano creators (under 10K subs) | B27: at least 3 | C27: =COUNTIF(Creators!$F$5:$F$22,"<10000") | D27: ="review"
A28: Distinct categories | B28: at least 8 | C28: =SUMPRODUCT(1/COUNTIF(Creators!$D$5:$D$22,Creators!$D$5:$D$22)) | D28: ="review"

Sheet Feature benchmarks
A1: Feature benchmarks
A2: A raw number means nothing on its own: 4% engagement is weak for a Nano creator and strong for a Mid-tier one. These tables are what turn a metric into a judgement, and they are what the fit score reads.
A4: 1. TIER BENCHMARKS
A5: tier | B5: sub range | C5: engagement benchmark | D5: engagement floor | E5: view-to-sub floor | F5: cost per 1k views (typical) | G5: flag as poor value above
A6: Nano | B6: under 10K | C6: 0.1 | D6: 0.07 | E6: 0.45 | F6: 100 | G6: 130
A7: Micro | B7: 10K - 100K | C7: 0.07 | D7: 0.045 | E7: 0.35 | F7: 78 | G7: 100
A8: Mid-tier | B8: 100K - 500K | C8: 0.05 | D8: 0.035 | E8: 0.3 | F8: 65 | G8: 85
A10: Benchmarks are the medians of this roster, set to mirror the real pattern: smaller audiences engage more and cost more per view.
A12: 2. CATEGORY AFFINITY - demo campaign vertical: Food & Beverage
A13: category | B13: affinity (0-100) | C13: reasoning
A14: Food & Beverage | B14: 100 | C14: Same vertical.
A15: Cooking | B15: 90 | C15: Same audience intent, adjacent framing.
A16: Health & Lifestyle | B16: 65 | C16: Food appears regularly inside lifestyle content.
A17: Parenting & Family | B17: 55 | C17: Family meals and grocery decisions overlap.
A18: Fitness | B18: 45 | C18: Nutrition adjacency, but the framing is performance not pleasure.
A19: Beauty & Skincare | B19: 25 | C19: Shared demographic, unrelated purchase intent.
A20: Fashion & Beauty | B20: 25 | C20: Shared demographic, unrelated purchase intent.
A21: Outdoor & Gear | B21: 20 | C21: Occasional camp-food overlap only.
A22: Tech Reviews | B22: 10 | C22: No meaningful overlap.
A23: Gaming | B23: 10 | C23: No meaningful overlap.
A24: Personal Finance | B24: 5 | C24: No overlap, and higher claim risk.
A26: Replace this column when the campaign vertical changes. Everything downstream recalculates.
A28: 3. AUDIENCE AGE OVERLAP - demo campaign target: 25-34
A29: creator age band | B29: overlap points (max 35) | C29: reasoning
A30: 25-34 | B30: 35 | C30: Exact match.
A31: 25-44 | B31: 28 | C31: Fully contains the target band, diluted by older viewers.
A32: 18-34 | B32: 25 | C32: Contains the target band, diluted by younger viewers.
A33: 30-44 | B33: 18 | C33: Partial overlap at the upper edge.
A34: 18-24 | B34: 5 | C34: Almost no overlap.
A36: 4. FIT SCORE WEIGHTS
A37: feature | B37: weight | C37: what it answers
A38: Category affinity | B38: 0.25 | C38: Does this creator's subject matter carry the product at all?
A39: Engagement vs tier benchmark | B39: 0.2 | C39: Does the audience actually respond, judged against creators of the same size?
A40: Audience fit | B40: 0.2 | C40: Are these the right viewers by age and geography?
A41: Value vs tier benchmark | B41: 0.15 | C41: Is the price fair for the reach delivered?
A42: Brand safety | B42: 0.15 | C42: What is the reputational exposure?
A43: Sponsor saturation | B43: 0.05 | C43: How ad-fatigued is this audience already?
A44: Total | B44: =SUM(B38:B43)

Sheet Fit score
A1: Campaign fit score - worked example
A2: Every sub-score recalculates from the Creators tab and the benchmark tables. Change a weight or a campaign parameter and the ranking moves - which is what makes this a scoring model rather than a list of opinions.
A4: CAMPAIGN PARAMETERS
A5: Vertical | B5: Food & Beverage
A6: Target age band | B6: 25-34
A7: Target country | B7: US
A8: Budget - dedicated video | B8: 5000
A9: Minimum safety score | B9: 80
A11: Sub-scores are 0-100. Reaching the tier benchmark scores 70, so exceeding it is rewarded and falling short is penalised, without letting one feature dominate.
A13: creator | B13: category | C13: tier | D13: category affinity | E13: engagement | F13: audience | G13: value | H13: safety | I13: saturation | J13: FIT SCORE | K13: rank | L13: within budget
A14: =Creators!B5 | B14: =Creators!D5 | C14: =Creators!E5 | D14: =INDEX('Feature benchmarks'!$B$14:$B$24,MATCH(B14,'Feature benchmarks'!$A$14:$A$24,0)) | E14: =MIN(100,ROUND(Creators!H5/INDEX('Feature benchmarks'!$C$6:$C$8,MATCH(C14,'Feature benchmarks'!$A$6:$A$8,0))*70,0)) | F14: =40+INDEX('Feature benchmarks'!$B$30:$B$34,MATCH(Creators!L5,'Feature benchmarks'!$A$30:$A$34,0))+IF(Creators!N5=$B$7,25,10) | G14: =MIN(100,ROUND(INDEX('Feature benchmarks'!$F$6:$F$8,MATCH(C14,'Feature benchmarks'!$A$6:$A$8,0))/Creators!T5*70,0)) | H14: =Creators!K5 | I14: =ROUND(100-COUNTIFS(RecentVideos!$A$5:$A$58,Creators!A5,RecentVideos!$H$5:$H$58,"TRUE")/COUNTIF(RecentVideos!$A$5:$A$58,Creators!A5)*100,0) | J14: =ROUND(D14*'Feature benchmarks'!$B$38+E14*'Feature benchmarks'!$B$39+F14*'Feature benchmarks'!$B$40+G14*'Feature benchmarks'!$B$41+H14*'Feature benchmarks'!$B$42+I14*'Feature benchmarks'!$B$43,1) | K14: =RANK(J14,$J$14:$J$31,0) | L14: =IF(Creators!R5<=$B$8,"Yes","Over budget")
A15: =Creators!B6 | B15: =Creators!D6 | C15: =Creators!E6 | D15: =INDEX('Feature benchmarks'!$B$14:$B$24,MATCH(B15,'Feature benchmarks'!$A$14:$A$24,0)) | E15: =MIN(100,ROUND(Creators!H6/INDEX('Feature benchmarks'!$C$6:$C$8,MATCH(C15,'Feature benchmarks'!$A$6:$A$8,0))*70,0)) | F15: =40+INDEX('Feature benchmarks'!$B$30:$B$34,MATCH(Creators!L6,'Feature benchmarks'!$A$30:$A$34,0))+IF(Creators!N6=$B$7,25,10) | G15: =MIN(100,ROUND(INDEX('Feature benchmarks'!$F$6:$F$8,MATCH(C15,'Feature benchmarks'!$A$6:$A$8,0))/Creators!T6*70,0)) | H15: =Creators!K6 | I15: =ROUND(100-COUNTIFS(RecentVideos!$A$5:$A$58,Creators!A6,RecentVideos!$H$5:$H$58,"TRUE")/COUNTIF(RecentVideos!$A$5:$A$58,Creators!A6)*100,0) | J15: =ROUND(D15*'Feature benchmarks'!$B$38+E15*'Feature benchmarks'!$B$39+F15*'Feature benchmarks'!$B$40+G15*'Feature benchmarks'!$B$41+H15*'Feature benchmarks'!$B$42+I15*'Feature benchmarks'!$B$43,1) | K15: =RANK(J15,$J$14:$J$31,0) | L15: =IF(Creators!R6<=$B$8,"Yes","Over budget")
A16: =Creators!B7 | B16: =Creators!D7 | C16: =Creators!E7 | D16: =INDEX('Feature benchmarks'!$B$14:$B$24,MATCH(B16,'Feature benchmarks'!$A$14:$A$24,0)) | E16: =MIN(100,ROUND(Creators!H7/INDEX('Feature benchmarks'!$C$6:$C$8,MATCH(C16,'Feature benchmarks'!$A$6:$A$8,0))*70,0)) | F16: =40+INDEX('Feature benchmarks'!$B$30:$B$34,MATCH(Creators!L7,'Feature benchmarks'!$A$30:$A$34,0))+IF(Creators!N7=$B$7,25,10) | G16: =MIN(100,ROUND(INDEX('Feature benchmarks'!$F$6:$F$8,MATCH(C16,'Feature benchmarks'!$A$6:$A$8,0))/Creators!T7*70,0)) | H16: =Creators!K7 | I16: =ROUND(100-COUNTIFS(RecentVideos!$A$5:$A$58,Creators!A7,RecentVideos!$H$5:$H$58,"TRUE")/COUNTIF(RecentVideos!$A$5:$A$58,Creators!A7)*100,0) | J16: =ROUND(D16*'Feature benchmarks'!$B$38+E16*'Feature benchmarks'!$B$39+F16*'Feature benchmarks'!$B$40+G16*'Feature benchmarks'!$B$41+H16*'Feature benchmarks'!$B$42+I16*'Feature benchmarks'!$B$43,1) | K16: =RANK(J16,$J$14:$J$31,0) | L16: =IF(Creators!R7<=$B$8,"Yes","Over budget")
A17: =Creators!B8 | B17: =Creators!D8 | C17: =Creators!E8 | D17: =INDEX('Feature benchmarks'!$B$14:$B$24,MATCH(B17,'Feature benchmarks'!$A$14:$A$24,0)) | E17: =MIN(100,ROUND(Creators!H8/INDEX('Feature benchmarks'!$C$6:$C$8,MATCH(C17,'Feature benchmarks'!$A$6:$A$8,0))*70,0)) | F17: =40+INDEX('Feature benchmarks'!$B$30:$B$34,MATCH(Creators!L8,'Feature benchmarks'!$A$30:$A$34,0))+IF(Creators!N8=$B$7,25,10) | G17: =MIN(100,ROUND(INDEX('Feature benchmarks'!$F$6:$F$8,MATCH(C17,'Feature benchmarks'!$A$6:$A$8,0))/Creators!T8*70,0)) | H17: =Creators!K8 | I17: =ROUND(100-COUNTIFS(RecentVideos!$A$5:$A$58,Creators!A8,RecentVideos!$H$5:$H$58,"TRUE")/COUNTIF(RecentVideos!$A$5:$A$58,Creators!A8)*100,0) | J17: =ROUND(D17*'Feature benchmarks'!$B$38+E17*'Feature benchmarks'!$B$39+F17*'Feature benchmarks'!$B$40+G17*'Feature benchmarks'!$B$41+H17*'Feature benchmarks'!$B$42+I17*'Feature benchmarks'!$B$43,1) | K17: =RANK(J17,$J$14:$J$31,0) | L17: =IF(Creators!R8<=$B$8,"Yes","Over budget")
A18: =Creators!B9 | B18: =Creators!D9 | C18: =Creators!E9 | D18: =INDEX('Feature benchmarks'!$B$14:$B$24,MATCH(B18,'Feature benchmarks'!$A$14:$A$24,0)) | E18: =MIN(100,ROUND(Creators!H9/INDEX('Feature benchmarks'!$C$6:$C$8,MATCH(C18,'Feature benchmarks'!$A$6:$A$8,0))*70,0)) | F18: =40+INDEX('Feature benchmarks'!$B$30:$B$34,MATCH(Creators!L9,'Feature benchmarks'!$A$30:$A$34,0))+IF(Creators!N9=$B$7,25,10) | G18: =MIN(100,ROUND(INDEX('Feature benchmarks'!$F$6:$F$8,MATCH(C18,'Feature benchmarks'!$A$6:$A$8,0))/Creators!T9*70,0)) | H18: =Creators!K9 | I18: =ROUND(100-COUNTIFS(RecentVideos!$A$5:$A$58,Creators!A9,RecentVideos!$H$5:$H$58,"TRUE")/COUNTIF(RecentVideos!$A$5:$A$58,Creators!A9)*100,0) | J18: =ROUND(D18*'Feature benchmarks'!$B$38+E18*'Feature benchmarks'!$B$39+F18*'Feature benchmarks'!$B$40+G18*'Feature benchmarks'!$B$41+H18*'Feature benchmarks'!$B$42+I18*'Feature benchmarks'!$B$43,1) | K18: =RANK(J18,$J$14:$J$31,0) | L18: =IF(Creators!R9<=$B$8,"Yes","Over budget")
A19: =Creators!B10 | B19: =Creators!D10 | C19: =Creators!E10 | D19: =INDEX('Feature benchmarks'!$B$14:$B$24,MATCH(B19,'Feature benchmarks'!$A$14:$A$24,0)) | E19: =MIN(100,ROUND(Creators!H10/INDEX('Feature benchmarks'!$C$6:$C$8,MATCH(C19,'Feature benchmarks'!$A$6:$A$8,0))*70,0)) | F19: =40+INDEX('Feature benchmarks'!$B$30:$B$34,MATCH(Creators!L10,'Feature benchmarks'!$A$30:$A$34,0))+IF(Creators!N10=$B$7,25,10) | G19: =MIN(100,ROUND(INDEX('Feature benchmarks'!$F$6:$F$8,MATCH(C19,'Feature benchmarks'!$A$6:$A$8,0))/Creators!T10*70,0)) | H19: =Creators!K10 | I19: =ROUND(100-COUNTIFS(RecentVideos!$A$5:$A$58,Creators!A10,RecentVideos!$H$5:$H$58,"TRUE")/COUNTIF(RecentVideos!$A$5:$A$58,Creators!A10)*100,0) | J19: =ROUND(D19*'Feature benchmarks'!$B$38+E19*'Feature benchmarks'!$B$39+F19*'Feature benchmarks'!$B$40+G19*'Feature benchmarks'!$B$41+H19*'Feature benchmarks'!$B$42+I19*'Feature benchmarks'!$B$43,1) | K19: =RANK(J19,$J$14:$J$31,0) | L19: =IF(Creators!R10<=$B$8,"Yes","Over budget")
A20: =Creators!B11 | B20: =Creators!D11 | C20: =Creators!E11 | D20: =INDEX('Feature benchmarks'!$B$14:$B$24,MATCH(B20,'Feature benchmarks'!$A$14:$A$24,0)) | E20: =MIN(100,ROUND(Creators!H11/INDEX('Feature benchmarks'!$C$6:$C$8,MATCH(C20,'Feature benchmarks'!$A$6:$A$8,0))*70,0)) | F20: =40+INDEX('Feature benchmarks'!$B$30:$B$34,MATCH(Creators!L11,'Feature benchmarks'!$A$30:$A$34,0))+IF(Creators!N11=$B$7,25,10) | G20: =MIN(100,ROUND(INDEX('Feature benchmarks'!$F$6:$F$8,MATCH(C20,'Feature benchmarks'!$A$6:$A$8,0))/Creators!T11*70,0)) | H20: =Creators!K11 | I20: =ROUND(100-COUNTIFS(RecentVideos!$A$5:$A$58,Creators!A11,RecentVideos!$H$5:$H$58,"TRUE")/COUNTIF(RecentVideos!$A$5:$A$58,Creators!A11)*100,0) | J20: =ROUND(D20*'Feature benchmarks'!$B$38+E20*'Feature benchmarks'!$B$39+F20*'Feature benchmarks'!$B$40+G20*'Feature benchmarks'!$B$41+H20*'Feature benchmarks'!$B$42+I20*'Feature benchmarks'!$B$43,1) | K20: =RANK(J20,$J$14:$J$31,0) | L20: =IF(Creators!R11<=$B$8,"Yes","Over budget")
A21: =Creators!B12 | B21: =Creators!D12 | C21: =Creators!E12 | D21: =INDEX('Feature benchmarks'!$B$14:$B$24,MATCH(B21,'Feature benchmarks'!$A$14:$A$24,0)) | E21: =MIN(100,ROUND(Creators!H12/INDEX('Feature benchmarks'!$C$6:$C$8,MATCH(C21,'Feature benchmarks'!$A$6:$A$8,0))*70,0)) | F21: =40+INDEX('Feature benchmarks'!$B$30:$B$34,MATCH(Creators!L12,'Feature benchmarks'!$A$30:$A$34,0))+IF(Creators!N12=$B$7,25,10) | G21: =MIN(100,ROUND(INDEX('Feature benchmarks'!$F$6:$F$8,MATCH(C21,'Feature benchmarks'!$A$6:$A$8,0))/Creators!T12*70,0)) | H21: =Creators!K12 | I21: =ROUND(100-COUNTIFS(RecentVideos!$A$5:$A$58,Creators!A12,RecentVideos!$H$5:$H$58,"TRUE")/COUNTIF(RecentVideos!$A$5:$A$58,Creators!A12)*100,0) | J21: =ROUND(D21*'Feature benchmarks'!$B$38+E21*'Feature benchmarks'!$B$39+F21*'Feature benchmarks'!$B$40+G21*'Feature benchmarks'!$B$41+H21*'Feature benchmarks'!$B$42+I21*'Feature benchmarks'!$B$43,1) | K21: =RANK(J21,$J$14:$J$31,0) | L21: =IF(Creators!R12<=$B$8,"Yes","Over budget")
A22: =Creators!B13 | B22: =Creators!D13 | C22: =Creators!E13 | D22: =INDEX('Feature benchmarks'!$B$14:$B$24,MATCH(B22,'Feature benchmarks'!$A$14:$A$24,0)) | E22: =MIN(100,ROUND(Creators!H13/INDEX('Feature benchmarks'!$C$6:$C$8,MATCH(C22,'Feature benchmarks'!$A$6:$A$8,0))*70,0)) | F22: =40+INDEX('Feature benchmarks'!$B$30:$B$34,MATCH(Creators!L13,'Feature benchmarks'!$A$30:$A$34,0))+IF(Creators!N13=$B$7,25,10) | G22: =MIN(100,ROUND(INDEX('Feature benchmarks'!$F$6:$F$8,MATCH(C22,'Feature benchmarks'!$A$6:$A$8,0))/Creators!T13*70,0)) | H22: =Creators!K13 | I22: =ROUND(100-COUNTIFS(RecentVideos!$A$5:$A$58,Creators!A13,RecentVideos!$H$5:$H$58,"TRUE")/COUNTIF(RecentVideos!$A$5:$A$58,Creators!A13)*100,0) | J22: =ROUND(D22*'Feature benchmarks'!$B$38+E22*'Feature benchmarks'!$B$39+F22*'Feature benchmarks'!$B$40+G22*'Feature benchmarks'!$B$41+H22*'Feature benchmarks'!$B$42+I22*'Feature benchmarks'!$B$43,1) | K22: =RANK(J22,$J$14:$J$31,0) | L22: =IF(Creators!R13<=$B$8,"Yes","Over budget")
A23: =Creators!B14 | B23: =Creators!D14 | C23: =Creators!E14 | D23: =INDEX('Feature benchmarks'!$B$14:$B$24,MATCH(B23,'Feature benchmarks'!$A$14:$A$24,0)) | E23: =MIN(100,ROUND(Creators!H14/INDEX('Feature benchmarks'!$C$6:$C$8,MATCH(C23,'Feature benchmarks'!$A$6:$A$8,0))*70,0)) | F23: =40+INDEX('Feature benchmarks'!$B$30:$B$34,MATCH(Creators!L14,'Feature benchmarks'!$A$30:$A$34,0))+IF(Creators!N14=$B$7,25,10) | G23: =MIN(100,ROUND(INDEX('Feature benchmarks'!$F$6:$F$8,MATCH(C23,'Feature benchmarks'!$A$6:$A$8,0))/Creators!T14*70,0)) | H23: =Creators!K14 | I23: =ROUND(100-COUNTIFS(RecentVideos!$A$5:$A$58,Creators!A14,RecentVideos!$H$5:$H$58,"TRUE")/COUNTIF(RecentVideos!$A$5:$A$58,Creators!A14)*100,0) | J23: =ROUND(D23*'Feature benchmarks'!$B$38+E23*'Feature benchmarks'!$B$39+F23*'Feature benchmarks'!$B$40+G23*'Feature benchmarks'!$B$41+H23*'Feature benchmarks'!$B$42+I23*'Feature benchmarks'!$B$43,1) | K23: =RANK(J23,$J$14:$J$31,0) | L23: =IF(Creators!R14<=$B$8,"Yes","Over budget")
A24: =Creators!B15 | B24: =Creators!D15 | C24: =Creators!E15 | D24: =INDEX('Feature benchmarks'!$B$14:$B$24,MATCH(B24,'Feature benchmarks'!$A$14:$A$24,0)) | E24: =MIN(100,ROUND(Creators!H15/INDEX('Feature benchmarks'!$C$6:$C$8,MATCH(C24,'Feature benchmarks'!$A$6:$A$8,0))*70,0)) | F24: =40+INDEX('Feature benchmarks'!$B$30:$B$34,MATCH(Creators!L15,'Feature benchmarks'!$A$30:$A$34,0))+IF(Creators!N15=$B$7,25,10) | G24: =MIN(100,ROUND(INDEX('Feature benchmarks'!$F$6:$F$8,MATCH(C24,'Feature benchmarks'!$A$6:$A$8,0))/Creators!T15*70,0)) | H24: =Creators!K15 | I24: =ROUND(100-COUNTIFS(RecentVideos!$A$5:$A$58,Creators!A15,RecentVideos!$H$5:$H$58,"TRUE")/COUNTIF(RecentVideos!$A$5:$A$58,Creators!A15)*100,0) | J24: =ROUND(D24*'Feature benchmarks'!$B$38+E24*'Feature benchmarks'!$B$39+F24*'Feature benchmarks'!$B$40+G24*'Feature benchmarks'!$B$41+H24*'Feature benchmarks'!$B$42+I24*'Feature benchmarks'!$B$43,1) | K24: =RANK(J24,$J$14:$J$31,0) | L24: =IF(Creators!R15<=$B$8,"Yes","Over budget")
A25: =Creators!B16 | B25: =Creators!D16 | C25: =Creators!E16 | D25: =INDEX('Feature benchmarks'!$B$14:$B$24,MATCH(B25,'Feature benchmarks'!$A$14:$A$24,0)) | E25: =MIN(100,ROUND(Creators!H16/INDEX('Feature benchmarks'!$C$6:$C$8,MATCH(C25,'Feature benchmarks'!$A$6:$A$8,0))*70,0)) | F25: =40+INDEX('Feature benchmarks'!$B$30:$B$34,MATCH(Creators!L16,'Feature benchmarks'!$A$30:$A$34,0))+IF(Creators!N16=$B$7,25,10) | G25: =MIN(100,ROUND(INDEX('Feature benchmarks'!$F$6:$F$8,MATCH(C25,'Feature benchmarks'!$A$6:$A$8,0))/Creators!T16*70,0)) | H25: =Creators!K16 | I25: =ROUND(100-COUNTIFS(RecentVideos!$A$5:$A$58,Creators!A16,RecentVideos!$H$5:$H$58,"TRUE")/COUNTIF(RecentVideos!$A$5:$A$58,Creators!A16)*100,0) | J25: =ROUND(D25*'Feature benchmarks'!$B$38+E25*'Feature benchmarks'!$B$39+F25*'Feature benchmarks'!$B$40+G25*'Feature benchmarks'!$B$41+H25*'Feature benchmarks'!$B$42+I25*'Feature benchmarks'!$B$43,1) | K25: =RANK(J25,$J$14:$J$31,0) | L25: =IF(Creators!R16<=$B$8,"Yes","Over budget")
... A31: =Creators!B22 | B31: =Creators!D22 | C31: =Creators!E22 | D31: =INDEX('Feature benchmarks'!$B$14:$B$24,MATCH(B31,'Feature benchmarks'!$A$14:$A$24,0)) | E31: =MIN(100,ROUND(Creators!H22/INDEX('Feature benchmarks'!$C$6:$C$8,MATCH(C31,'Feature benchmarks'!$A$6:$A$8,0))*70,0)) | F31: =40+INDEX('Feature benchmarks'!$B$30:$B$34,MATCH(Creators!L22,'Feature benchmarks'!$A$30:$A$34,0))+IF(Creators!N22=$B$7,25,10) | G31: =MIN(100,ROUND(INDEX('Feature benchmarks'!$F$6:$F$8,MATCH(C31,'Feature benchmarks'!$A$6:$A$8,0))/Creators!T22*70,0)) | H31: =Creators!K22 | I31: =ROUND(100-COUNTIFS(RecentVideos!$A$5:$A$58,Creators!A22,RecentVideos!$H$5:$H$58,"TRUE")/COUNTIF(RecentVideos!$A$5:$A$58,Creators!A22)*100,0) | J31: =ROUND(D31*'Feature benchmarks'!$B$38+E31*'Feature benchmarks'!$B$39+F31*'Feature benchmarks'!$B$40+G31*'Feature benchmarks'!$B$41+H31*'Feature benchmarks'!$B$42+I31*'Feature benchmarks'!$B$43,1) | K31: =RANK(J31,$J$14:$J$31,0) | L31: =IF(Creators!R22<=$B$8,"Yes","Over budget")
A32: =Creators!B23 | B32: =Creators!D23 | C32: =Creators!E23 | D32: =INDEX('Feature benchmarks'!$B$14:$B$24,MATCH(B32,'Feature benchmarks'!$A$14:$A$24,0)) | E32: =MIN(100,ROUND(Creators!H23/INDEX('Feature benchmarks'!$C$6:$C$8,MATCH(C32,'Feature benchmarks'!$A$6:$A$8,0))*70,0)) | F32: =40+INDEX('Feature benchmarks'!$B$30:$B$34,MATCH(Creators!L23,'Feature benchmarks'!$A$30:$A$34,0))+IF(Creators!N23=$B$7,25,10) | G32: =MIN(100,ROUND(INDEX('Feature benchmarks'!$F$6:$F$8,MATCH(C32,'Feature benchmarks'!$A$6:$A$8,0))/Creators!T23*70,0)) | H32: =Creators!K23 | I32: =ROUND(100-COUNTIFS(RecentVideos!$A$5:$A$154,Creators!A23,RecentVideos!$H$5:$H$154,"TRUE")/COUNTIF(RecentVideos!$A$5:$A$154,Creators!A23)*100,0) | J32: =ROUND(D32*'Feature benchmarks'!$B$38+E32*'Feature benchmarks'!$B$39+F32*'Feature benchmarks'!$B$40+G32*'Feature benchmarks'!$B$41+H32*'Feature benchmarks'!$B$42+I32*'Feature benchmarks'!$B$43,1)
A33: =Creators!B24 | B33: =Creators!D24 | C33: =Creators!E24 | D33: =INDEX('Feature benchmarks'!$B$14:$B$24,MATCH(B33,'Feature benchmarks'!$A$14:$A$24,0)) | E33: =MIN(100,ROUND(Creators!H24/INDEX('Feature benchmarks'!$C$6:$C$8,MATCH(C33,'Feature benchmarks'!$A$6:$A$8,0))*70,0)) | F33: =40+INDEX('Feature benchmarks'!$B$30:$B$34,MATCH(Creators!L24,'Feature benchmarks'!$A$30:$A$34,0))+IF(Creators!N24=$B$7,25,10) | G33: =MIN(100,ROUND(INDEX('Feature benchmarks'!$F$6:$F$8,MATCH(C33,'Feature benchmarks'!$A$6:$A$8,0))/Creators!T24*70,0)) | H33: =Creators!K24 | I33: =ROUND(100-COUNTIFS(RecentVideos!$A$5:$A$154,Creators!A24,RecentVideos!$H$5:$H$154,"TRUE")/COUNTIF(RecentVideos!$A$5:$A$154,Creators!A24)*100,0) | J33: =ROUND(D33*'Feature benchmarks'!$B$38+E33*'Feature benchmarks'!$B$39+F33*'Feature benchmarks'!$B$40+G33*'Feature benchmarks'!$B$41+H33*'Feature benchmarks'!$B$42+I33*'Feature benchmarks'!$B$43,1)
A34: =Creators!B25 | B34: =Creators!D25 | C34: =Creators!E25 | D34: =INDEX('Feature benchmarks'!$B$14:$B$24,MATCH(B34,'Feature benchmarks'!$A$14:$A$24,0)) | E34: =MIN(100,ROUND(Creators!H25/INDEX('Feature benchmarks'!$C$6:$C$8,MATCH(C34,'Feature benchmarks'!$A$6:$A$8,0))*70,0)) | F34: =40+INDEX('Feature benchmarks'!$B$30:$B$34,MATCH(Creators!L25,'Feature benchmarks'!$A$30:$A$34,0))+IF(Creators!N25=$B$7,25,10) | G34: =MIN(100,ROUND(INDEX('Feature benchmarks'!$F$6:$F$8,MATCH(C34,'Feature benchmarks'!$A$6:$A$8,0))/Creators!T25*70,0)) | H34: =Creators!K25 | I34: =ROUND(100-COUNTIFS(RecentVideos!$A$5:$A$154,Creators!A25,RecentVideos!$H$5:$H$154,"TRUE")/COUNTIF(RecentVideos!$A$5:$A$154,Creators!A25)*100,0) | J34: =ROUND(D34*'Feature benchmarks'!$B$38+E34*'Feature benchmarks'!$B$39+F34*'Feature benchmarks'!$B$40+G34*'Feature benchmarks'!$B$41+H34*'Feature benchmarks'!$B$42+I34*'Feature benchmarks'!$B$43,1)
A35: =Creators!B26 | B35: =Creators!D26 | C35: =Creators!E26 | D35: =INDEX('Feature benchmarks'!$B$14:$B$24,MATCH(B35,'Feature benchmarks'!$A$14:$A$24,0)) | E35: =MIN(100,ROUND(Creators!H26/INDEX('Feature benchmarks'!$C$6:$C$8,MATCH(C35,'Feature benchmarks'!$A$6:$A$8,0))*70,0)) | F35: =40+INDEX('Feature benchmarks'!$B$30:$B$34,MATCH(Creators!L26,'Feature benchmarks'!$A$30:$A$34,0))+IF(Creators!N26=$B$7,25,10) | G35: =MIN(100,ROUND(INDEX('Feature benchmarks'!$F$6:$F$8,MATCH(C35,'Feature benchmarks'!$A$6:$A$8,0))/Creators!T26*70,0)) | H35: =Creators!K26 | I35: =ROUND(100-COUNTIFS(RecentVideos!$A$5:$A$154,Creators!A26,RecentVideos!$H$5:$H$154,"TRUE")/COUNTIF(RecentVideos!$A$5:$A$154,Creators!A26)*100,0) | J35: =ROUND(D35*'Feature benchmarks'!$B$38+E35*'Feature benchmarks'!$B$39+F35*'Feature benchmarks'!$B$40+G35*'Feature benchmarks'!$B$41+H35*'Feature benchmarks'!$B$42+I35*'Feature benchmarks'!$B$43,1)
A36: =Creators!B27 | B36: =Creators!D27 | C36: =Creators!E27 | D36: =INDEX('Feature benchmarks'!$B$14:$B$24,MATCH(B36,'Feature benchmarks'!$A$14:$A$24,0)) | E36: =MIN(100,ROUND(Creators!H27/INDEX('Feature benchmarks'!$C$6:$C$8,MATCH(C36,'Feature benchmarks'!$A$6:$A$8,0))*70,0)) | F36: =40+INDEX('Feature benchmarks'!$B$30:$B$34,MATCH(Creators!L27,'Feature benchmarks'!$A$30:$A$34,0))+IF(Creators!N27=$B$7,25,10) | G36: =MIN(100,ROUND(INDEX('Feature benchmarks'!$F$6:$F$8,MATCH(C36,'Feature benchmarks'!$A$6:$A$8,0))/Creators!T27*70,0)) | H36: =Creators!K27 | I36: =ROUND(100-COUNTIFS(RecentVideos!$A$5:$A$154,Creators!A27,RecentVideos!$H$5:$H$154,"TRUE")/COUNTIF(RecentVideos!$A$5:$A$154,Creators!A27)*100,0) | J36: =ROUND(D36*'Feature benchmarks'!$B$38+E36*'Feature benchmarks'!$B$39+F36*'Feature benchmarks'!$B$40+G36*'Feature benchmarks'!$B$41+H36*'Feature benchmarks'!$B$42+I36*'Feature benchmarks'!$B$43,1)
A37: =Creators!B28 | B37: =Creators!D28 | C37: =Creators!E28 | D37: =INDEX('Feature benchmarks'!$B$14:$B$24,MATCH(B37,'Feature benchmarks'!$A$14:$A$24,0)) | E37: =MIN(100,ROUND(Creators!H28/INDEX('Feature benchmarks'!$C$6:$C$8,MATCH(C37,'Feature benchmarks'!$A$6:$A$8,0))*70,0)) | F37: =40+INDEX('Feature benchmarks'!$B$30:$B$34,MATCH(Creators!L28,'Feature benchmarks'!$A$30:$A$34,0))+IF(Creators!N28=$B$7,25,10) | G37: =MIN(100,ROUND(INDEX('Feature benchmarks'!$F$6:$F$8,MATCH(C37,'Feature benchmarks'!$A$6:$A$8,0))/Creators!T28*70,0)) | H37: =Creators!K28 | I37: =ROUND(100-COUNTIFS(RecentVideos!$A$5:$A$154,Creators!A28,RecentVideos!$H$5:$H$154,"TRUE")/COUNTIF(RecentVideos!$A$5:$A$154,Creators!A28)*100,0) | J37: =ROUND(D37*'Feature benchmarks'!$B$38+E37*'Feature benchmarks'!$B$39+F37*'Feature benchmarks'!$B$40+G37*'Feature benchmarks'!$B$41+H37*'Feature benchmarks'!$B$42+I37*'Feature benchmarks'!$B$43,1)
A38: =Creators!B29 | B38: =Creators!D29 | C38: =Creators!E29 | D38: =INDEX('Feature benchmarks'!$B$14:$B$24,MATCH(B38,'Feature benchmarks'!$A$14:$A$24,0)) | E38: =MIN(100,ROUND(Creators!H29/INDEX('Feature benchmarks'!$C$6:$C$8,MATCH(C38,'Feature benchmarks'!$A$6:$A$8,0))*70,0)) | F38: =40+INDEX('Feature benchmarks'!$B$30:$B$34,MATCH(Creators!L29,'Feature benchmarks'!$A$30:$A$34,0))+IF(Creators!N29=$B$7,25,10) | G38: =MIN(100,ROUND(INDEX('Feature benchmarks'!$F$6:$F$8,MATCH(C38,'Feature benchmarks'!$A$6:$A$8,0))/Creators!T29*70,0)) | H38: =Creators!K29 | I38: =ROUND(100-COUNTIFS(RecentVideos!$A$5:$A$154,Creators!A29,RecentVideos!$H$5:$H$154,"TRUE")/COUNTIF(RecentVideos!$A$5:$A$154,Creators!A29)*100,0) | J38: =ROUND(D38*'Feature benchmarks'!$B$38+E38*'Feature benchmarks'!$B$39+F38*'Feature benchmarks'!$B$40+G38*'Feature benchmarks'!$B$41+H38*'Feature benchmarks'!$B$42+I38*'Feature benchmarks'!$B$43,1)
A39: =Creators!B30 | B39: =Creators!D30 | C39: =Creators!E30 | D39: =INDEX('Feature benchmarks'!$B$14:$B$24,MATCH(B39,'Feature benchmarks'!$A$14:$A$24,0)) | E39: =MIN(100,ROUND(Creators!H30/INDEX('Feature benchmarks'!$C$6:$C$8,MATCH(C39,'Feature benchmarks'!$A$6:$A$8,0))*70,0)) | F39: =40+INDEX('Feature benchmarks'!$B$30:$B$34,MATCH(Creators!L30,'Feature benchmarks'!$A$30:$A$34,0))+IF(Creators!N30=$B$7,25,10) | G39: =MIN(100,ROUND(INDEX('Feature benchmarks'!$F$6:$F$8,MATCH(C39,'Feature benchmarks'!$A$6:$A$8,0))/Creators!T30*70,0)) | H39: =Creators!K30 | I39: =ROUND(100-COUNTIFS(RecentVideos!$A$5:$A$154,Creators!A30,RecentVideos!$H$5:$H$154,"TRUE")/COUNTIF(RecentVideos!$A$5:$A$154,Creators!A30)*100,0) | J39: =ROUND(D39*'Feature benchmarks'!$B$38+E39*'Feature benchmarks'!$B$39+F39*'Feature benchmarks'!$B$40+G39*'Feature benchmarks'!$B$41+H39*'Feature benchmarks'!$B$42+I39*'Feature benchmarks'!$B$43,1)
A40: =Creators!B31 | B40: =Creators!D31 | C40: =Creators!E31 | D40: =INDEX('Feature benchmarks'!$B$14:$B$24,MATCH(B40,'Feature benchmarks'!$A$14:$A$24,0)) | E40: =MIN(100,ROUND(Creators!H31/INDEX('Feature benchmarks'!$C$6:$C$8,MATCH(C40,'Feature benchmarks'!$A$6:$A$8,0))*70,0)) | F40: =40+INDEX('Feature benchmarks'!$B$30:$B$34,MATCH(Creators!L31,'Feature benchmarks'!$A$30:$A$34,0))+IF(Creators!N31=$B$7,25,10) | G40: =MIN(100,ROUND(INDEX('Feature benchmarks'!$F$6:$F$8,MATCH(C40,'Feature benchmarks'!$A$6:$A$8,0))/Creators!T31*70,0)) | H40: =Creators!K31 | I40: =ROUND(100-COUNTIFS(RecentVideos!$A$5:$A$154,Creators!A31,RecentVideos!$H$5:$H$154,"TRUE")/COUNTIF(RecentVideos!$A$5:$A$154,Creators!A31)*100,0) | J40: =ROUND(D40*'Feature benchmarks'!$B$38+E40*'Feature benchmarks'!$B$39+F40*'Feature benchmarks'!$B$40+G40*'Feature benchmarks'!$B$41+H40*'Feature benchmarks'!$B$42+I40*'Feature benchmarks'!$B$43,1)
A41: =Creators!B32 | B41: =Creators!D32 | C41: =Creators!E32 | D41: =INDEX('Feature benchmarks'!$B$14:$B$24,MATCH(B41,'Feature benchmarks'!$A$14:$A$24,0)) | E41: =MIN(100,ROUND(Creators!H32/INDEX('Feature benchmarks'!$C$6:$C$8,MATCH(C41,'Feature benchmarks'!$A$6:$A$8,0))*70,0)) | F41: =40+INDEX('Feature benchmarks'!$B$30:$B$34,MATCH(Creators!L32,'Feature benchmarks'!$A$30:$A$34,0))+IF(Creators!N32=$B$7,25,10) | G41: =MIN(100,ROUND(INDEX('Feature benchmarks'!$F$6:$F$8,MATCH(C41,'Feature benchmarks'!$A$6:$A$8,0))/Creators!T32*70,0)) | H41: =Creators!K32 | I41: =ROUND(100-COUNTIFS(RecentVideos!$A$5:$A$154,Creators!A32,RecentVideos!$H$5:$H$154,"TRUE")/COUNTIF(RecentVideos!$A$5:$A$154,Creators!A32)*100,0) | J41: =ROUND(D41*'Feature benchmarks'!$B$38+E41*'Feature benchmarks'!$B$39+F41*'Feature benchmarks'!$B$40+G41*'Feature benchmarks'!$B$41+H41*'Feature benchmarks'!$B$42+I41*'Feature benchmarks'!$B$43,1)
A42: =Creators!B33 | B42: =Creators!D33 | C42: =Creators!E33 | D42: =INDEX('Feature benchmarks'!$B$14:$B$24,MATCH(B42,'Feature benchmarks'!$A$14:$A$24,0)) | E42: =MIN(100,ROUND(Creators!H33/INDEX('Feature benchmarks'!$C$6:$C$8,MATCH(C42,'Feature benchmarks'!$A$6:$A$8,0))*70,0)) | F42: =40+INDEX('Feature benchmarks'!$B$30:$B$34,MATCH(Creators!L33,'Feature benchmarks'!$A$30:$A$34,0))+IF(Creators!N33=$B$7,25,10) | G42: =MIN(100,ROUND(INDEX('Feature benchmarks'!$F$6:$F$8,MATCH(C42,'Feature benchmarks'!$A$6:$A$8,0))/Creators!T33*70,0)) | H42: =Creators!K33 | I42: =ROUND(100-COUNTIFS(RecentVideos!$A$5:$A$154,Creators!A33,RecentVideos!$H$5:$H$154,"TRUE")/COUNTIF(RecentVideos!$A$5:$A$154,Creators!A33)*100,0) | J42: =ROUND(D42*'Feature benchmarks'!$B$38+E42*'Feature benchmarks'!$B$39+F42*'Feature benchmarks'!$B$40+G42*'Feature benchmarks'!$B$41+H42*'Feature benchmarks'!$B$42+I42*'Feature benchmarks'!$B$43,1)
A43: =Creators!B34 | B43: =Creators!D34 | C43: =Creators!E34 | D43: =INDEX('Feature benchmarks'!$B$14:$B$24,MATCH(B43,'Feature benchmarks'!$A$14:$A$24,0)) | E43: =MIN(100,ROUND(Creators!H34/INDEX('Feature benchmarks'!$C$6:$C$8,MATCH(C43,'Feature benchmarks'!$A$6:$A$8,0))*70,0)) | F43: =40+INDEX('Feature benchmarks'!$B$30:$B$34,MATCH(Creators!L34,'Feature benchmarks'!$A$30:$A$34,0))+IF(Creators!N34=$B$7,25,10) | G43: =MIN(100,ROUND(INDEX('Feature benchmarks'!$F$6:$F$8,MATCH(C43,'Feature benchmarks'!$A$6:$A$8,0))/Creators!T34*70,0)) | H43: =Creators!K34 | I43: =ROUND(100-COUNTIFS(RecentVideos!$A$5:$A$154,Creators!A34,RecentVideos!$H$5:$H$154,"TRUE")/COUNTIF(RecentVideos!$A$5:$A$154,Creators!A34)*100,0) | J43: =ROUND(D43*'Feature benchmarks'!$B$38+E43*'Feature benchmarks'!$B$39+F43*'Feature benchmarks'!$B$40+G43*'Feature benchmarks'!$B$41+H43*'Feature benchmarks'!$B$42+I43*'Feature benchmarks'!$B$43,1)
... A63: =Creators!B54 | B63: =Creators!D54 | C63: =Creators!E54 | D63: =INDEX('Feature benchmarks'!$B$14:$B$24,MATCH(B63,'Feature benchmarks'!$A$14:$A$24,0)) | E63: =MIN(100,ROUND(Creators!H54/INDEX('Feature benchmarks'!$C$6:$C$8,MATCH(C63,'Feature benchmarks'!$A$6:$A$8,0))*70,0)) | F63: =40+INDEX('Feature benchmarks'!$B$30:$B$34,MATCH(Creators!L54,'Feature benchmarks'!$A$30:$A$34,0))+IF(Creators!N54=$B$7,25,10) | G63: =MIN(100,ROUND(INDEX('Feature benchmarks'!$F$6:$F$8,MATCH(C63,'Feature benchmarks'!$A$6:$A$8,0))/Creators!T54*70,0)) | H63: =Creators!K54 | I63: =ROUND(100-COUNTIFS(RecentVideos!$A$5:$A$154,Creators!A54,RecentVideos!$H$5:$H$154,"TRUE")/COUNTIF(RecentVideos!$A$5:$A$154,Creators!A54)*100,0) | J63: =ROUND(D63*'Feature benchmarks'!$B$38+E63*'Feature benchmarks'!$B$39+F63*'Feature benchmarks'!$B$40+G63*'Feature benchmarks'!$B$41+H63*'Feature benchmarks'!$B$42+I63*'Feature benchmarks'!$B$43,1)
A65: Sanity check on the model: the two creators with the largest audiences should NOT automatically top this list, and a small, sharply-matched creator should be able to beat them. If that never happens, the weights are just re-ranking by follower count.

Sheet For import
A1: Paste-ready data for mockData.js
A2: Copy column A below and paste it straight into src/lib/mockData.js. Check the key names against the existing file first - if they differ, rename them here rather than changing the components.
A4: export const creators = [
A5: {
A6: "id": "maya-chen",
A7: "name": "Maya Chen",
A8: "handle": "@mayaeats",
A9: "category": "Food & Beverage",
A10: "tier": "Micro",
A11: "subscribers": 84000,
A12: "avgViews": 41000,
A13: "engagementRate": 0.072,
... A3952: ];
